mizuba/__init__.py
mizuba/_detect_conjunctions.py
mizuba/_dl_utils.py
mizuba/_logging.py
mizuba/_sgp4_polyjectory.py
mizuba/_version.py
mizuba/core.cpython-310-x86_64-linux-gnu.so
mizuba/data_sources/__init__.py
mizuba/data_sources/_celestrak.py
mizuba/data_sources/_common.py
mizuba/data_sources/_spacetrack.py
mizuba/test/__init__.py
mizuba/test/_common_heyoka_test.py
mizuba/test/_conj_wrapper.py
mizuba/test/_planar_circ.py
mizuba/test/_self_cross_utils.py
mizuba/test/_sgp4_satlist_setup.py
mizuba/test/disc_gpe_01.parquet
mizuba/test/iss_gpes.parquet
mizuba/test/multi_gpes.parquet
mizuba/test/single_gpe.parquet
mizuba/test/single_gpe_ds.parquet
mizuba/test/syncom_gpe.parquet
mizuba/test/test_boundary_cross_conjunctions.py
mizuba/test/test_boundary_self_conjunctions.py
mizuba/test/test_cross_conjunctions.py
mizuba/test/test_data_sources.py
mizuba/test/test_heyoka_cross_conjunctions.py
mizuba/test/test_heyoka_self_conjunctions.py
mizuba/test/test_make_sgp4_polyjectory.py
mizuba/test/test_polyjectory.py
mizuba/test/test_polytree.py
mizuba/test/test_self_conjunctions.py
mizuba/test/test_tmpdir.py
mizuba.libs/libboost_atomic-2af46582.so.1.86.0
mizuba.libs/libboost_charconv-04c82650.so.1.86.0
mizuba.libs/libboost_filesystem-4105561e.so.1.86.0
mizuba.libs/libboost_iostreams-14196135.so.1.86.0
mizuba.libs/libboost_serialization-f2e8fb3c.so.1.86.0
mizuba.libs/libcrypto-763383ec.so.3
mizuba.libs/libfmt-c6c3f7cb.so.11.0.2
mizuba.libs/libgmp-b256a283.so.10.5.0
mizuba.libs/libheyoka-b2a0fd69.so.35.0
mizuba.libs/libmp++-0aeb8127.so.16.0
mizuba.libs/libmpfr-2589270a.so.6.2.1
mizuba.libs/libsleef-8e07730b.so.3.7.0
mizuba.libs/libspdlog-aa4fe279.so.1.14.1
mizuba.libs/libssl-81b311e0.so.3
mizuba.libs/libtbb-85a72081.so.12.15
mizuba-0.0.16.dist-info/METADATA
mizuba-0.0.16.dist-info/WHEEL
mizuba-0.0.16.dist-info/RECORD
mizuba-0.0.16.dist-info/licenses/LICENSE
