Metadata-Version: 2.2
Name: mizuba
Version: 0.0.16
Summary: Python library for fast conjunction detection in orbital environments
Keywords: science,math,physics,astrodynamics,aerospace
Author-Email: Francesco Biscarni <bluescarni@gmail.com>
License: AGPL-3.0-or-later
Classifier: Development Status :: 3 - Alpha
Classifier: Operating System :: OS Independent
Classifier: Intended Audience :: Science/Research
Classifier: Topic :: Scientific/Engineering
Classifier: Topic :: Scientific/Engineering :: Mathematics
Classifier: Topic :: Scientific/Engineering :: Physics
Classifier: Programming Language :: Python :: 3
Project-URL: Documentation, https://github.com/bluescarni/mizuba
Project-URL: Repository, https://github.com/bluescarni/mizuba
Requires-Python: >=3.9
Requires-Dist: numpy
Requires-Dist: polars
Requires-Dist: requests
Requires-Dist: astropy
Provides-Extra: sgp4
Requires-Dist: sgp4; extra == "sgp4"
Provides-Extra: heyoka
Requires-Dist: heyoka<8,>=7.3.0; extra == "heyoka"
